tracardi_local_timespan/plugin.py
tracardi_local_timespan/model/configuration.py
tracardi_local_timespan/model/__pycache__/configuration.cpython-38.pyc
tracardi_local_timespan-0.6.0.dist-info/LICENSE.md
tracardi_local_timespan-0.6.0.dist-info/METADATA
tracardi_local_timespan-0.6.0.dist-info/WHEEL
tracardi_local_timespan-0.6.0.dist-info/top_level.txt
tracardi_local_timespan-0.6.0.dist-info/RECORD
